{"roomName":"tour ","startTime":"Thu May 07 2026 09:28:09 GMT-0700","songs":[{"songNumber":1,"songInfo":{"animeNames":{"english":"Mobile Suit Gundam 00","romaji":"Kidou Senshi Gundam 00"},"artist":"THE BACK HORN","composerInfo":{"groupId":80027450,"name":"THE BACK HORN"},"arrangerInfo":{"groupId":80027450,"name":"THE BACK HORN"},"songName":"Wana","type":2,"typeNumber":1,"annId":8190,"annSongId":8995,"highRisk":0,"animeScore":"7.8","animeType":"TV","vintage":"Fall 2007","animeDifficulty":30.70558774395418,"animeTags":["Military","Space","Male Protagonist","Primarily Male Cast","Politics","Ensemble Cast","War","Real Robot","Terrorism","Environmental","Dissociative Identities"],"animeGenre":["Action","Drama","Mecha","Sci-Fi"],"altAnimeNames":["Kidou Senshi Gundam 00","Kidou Senshi Gundam Double O","Mobile Suit Gundam 00"],"altAnimeNamesAnswers":[],"siteIds":{"annId":8190,"malId":2581,"kitsuId":2346,"aniListId":2581},"rebroadcast":0,"dub":0,"seasonInfo":{"name":"Season","number":"1.0"},"popularityRank":1593},"correctGuess":false,"wrongGuess":true,"answer":"kizuoibito (17641ms)","correctCount":0,"wrongCount":8,"startPoint":65,"videoLength":89.652,"videoUrl":"https://nawdist.animemusicquiz.com/zcu7v7.webm","correctGuessPlayers":[],"listStates":[{"name":"Diukes","status":2,"score":8},{"name":"xeyz","status":2,"score":8}]},{"songNumber":2,"songInfo":{"animeNames":{"english":"Id: Invaded","romaji":"Id: Invaded"},"artist":"MIYAVI","composerInfo":{"groupId":80022733,"name":"MIYAVI, Lenard Skolnik"},"arrangerInfo":{"groupId":80024819,"name":"MIYAVI & Yung Spielberg"},"songName":"UP","type":2,"typeNumber":2,"annId":22509,"annSongId":28687,"highRisk":1,"animeScore":"7.7","animeType":"TV","vintage":"Winter 2020","animeDifficulty":31.646211024278006,"animeTags":["Police","Male Protagonist","Tragedy","CGI","Gore","Time Manipulation","Female Protagonist","Anti-Hero","Cyberpunk","Primarily Adult Cast","Virtual World","Meta","Alternate Universe","Guns","Amnesia","Revenge","Urban Fantasy","Augmented Reality","Memory Manipulation","Philosophy","Crime","Detective","Prison"],"animeGenre":["Drama","Mystery","Psychological","Sci-Fi","Thriller"],"altAnimeNames":["Id: Invaded"],"altAnimeNamesAnswers":[],"siteIds":{"annId":22509,"malId":40046,"kitsuId":42436,"aniListId":110350},"rebroadcast":0,"dub":0,"seasonInfo":null,"popularityRank":525},"correctGuess":false,"wrongGuess":true,"answer":"air gear (13137ms)","correctCount":4,"wrongCount":4,"startPoint":52,"videoLength":89.936,"videoUrl":"https://nawdist.animemusicquiz.com/2kloev.webm","correctGuessPlayers":["Diukes","hubcioskubcio","tmokenc","xeyz"],"listStates":[{"name":"Diukes","status":2,"score":7},{"name":"tmokenc","status":2,"score":9},{"name":"xeyz","status":2,"score":9}]},{"songNumber":3,"songInfo":{"animeNames":{"english":"I'm Gonna Be an Angel!","romaji":"Tenshi ni Narumon!"},"artist":"Shizuru Ohtaka","composerInfo":{"artistId":564,"name":"Shizuru Ohtaka"},"arrangerInfo":{"artistId":10901,"name":"Yoshikazu Suo"},"songName":"Ai wa Umi","type":2,"typeNumber":1,"annId":278,"annSongId":802,"highRisk":0,"animeScore":"6.6","animeType":"TV","vintage":"Spring 1999","animeDifficulty":15.143544911012237,"animeTags":["Demons","Parody","Vampire","Family Life","Ensemble Cast","Nekomimi","Witch","Kemonomimi","Surreal Comedy","Urban Fantasy","Tanned Skin","Shapeshifting","Villainess","Heterosexual","Angels","Found Family"],"animeGenre":["Comedy","Fantasy","Romance"],"altAnimeNames":["Tenshi ni Narumon!","I'm Gonna Be an Angel!"],"altAnimeNamesAnswers":[],"siteIds":{"annId":278,"malId":605,"kitsuId":560,"aniListId":605},"rebroadcast":0,"dub":0,"seasonInfo":null,"popularityRank":5459},"correctGuess":false,"wrongGuess":true,"answer":"Please Save My Earth (17282ms)","correctCount":1,"wrongCount":7,"startPoint":44,"videoLength":85.009,"videoUrl":"https://nawdist.animemusicquiz.com/bq5l24.webm","correctGuessPlayers":["Diukes"],"listStates":[{"name":"xeyz","status":2,"score":8}]},{"songNumber":4,"songInfo":{"animeNames":{"english":"The Misfit of Demon King Academy II","romaji":"Maou Gakuin no Futekigousha II"},"artist":"Momosumomosu","composerInfo":{"artistId":7889,"name":"Momosumomosu"},"arrangerInfo":{"artistId":7889,"name":"Momosumomosu"},"songName":"Esoa (Ballad ver.)","type":2,"typeNumber":2,"annId":24105,"annSongId":40985,"highRisk":0,"animeScore":"6.8","animeType":"TV","vintage":"Winter 2023","animeDifficulty":27.90584381330182,"animeTags":["Demons","Female Harem","Magic","School","Super Power","Male Protagonist","Tragedy","Time Manipulation","Ensemble Cast","Reincarnation","Conspiracy","Twins","Kuudere","Heterosexual","Primarily Teen Cast","Marriage"],"animeGenre":["Action","Fantasy"],"altAnimeNames":["Maou Gakuin no Futekigousha II","The Misfit of Demon King Academy II"],"altAnimeNamesAnswers":[],"siteIds":{"annId":24105,"malId":48417,"kitsuId":44125,"aniListId":130588},"rebroadcast":0,"dub":0,"seasonInfo":{"name":"Season","number":"2.0"},"popularityRank":493},"correctGuess":true,"wrongGuess":false,"answer":"Maou Gakuin no Futekigousha II (3985ms)","correctCount":7,"wrongCount":1,"startPoint":24,"videoLength":96.61,"videoUrl":"https://nawdist.animemusicquiz.com/lx10dw.webm","correctGuessPlayers":["Diukes","hubcioskubcio","Swapin","Dry","inta","tmokenc","xeyz"],"listStates":[{"name":"hubcioskubcio","status":1,"score":0},{"name":"Dry","status":2,"score":4},{"name":"tmokenc","status":2,"score":6},{"name":"xeyz","status":2,"score":6}]},{"songNumber":5,"songInfo":{"animeNames":{"english":"Theatre of Darkness: Yamishibai","romaji":"Yami Shibai"},"artist":"imai feat.Pecori","composerInfo":{"groupId":80022059,"name":"imai feat.Pecori"},"arrangerInfo":{"groupId":80022059,"name":"imai feat.Pecori"},"songName":"Twilight","type":2,"typeNumber":1,"annId":23857,"annSongId":31906,"highRisk":0,"animeScore":"5.3","animeType":"TV","vintage":"Winter 2021","animeDifficulty":29.826217805151177,"animeTags":["Episodic","Ghost","Youkai"],"animeGenre":["Horror","Supernatural"],"altAnimeNames":["Yami Shibai","Theatre of Darkness: Yamishibai"],"altAnimeNamesAnswers":[],"siteIds":{"annId":23857,"malId":44208,"kitsuId":43797,"aniListId":126678},"rebroadcast":0,"dub":0,"seasonInfo":{"name":"Season","number":"8.0"},"popularityRank":4709},"correctGuess":false,"wrongGuess":true,"answer":"free a d (20203ms)","correctCount":3,"wrongCount":5,"startPoint":9,"videoLength":29.989,"videoUrl":"https://nawdist.animemusicquiz.com/2jynd8.webm","correctGuessPlayers":["Diukes","2skr","tmokenc"],"listStates":[{"name":"2skr","status":2,"score":0}]},{"songNumber":6,"songInfo":{"animeNames":{"english":"Inazuma Eleven: Reloaded","romaji":"Inazuma Eleven: Reloaded"},"artist":"kicks","composerInfo":{"artistId":14357,"name":"Takashi Aoki"},"arrangerInfo":{"artistId":12497,"name":"Tomoki Kikuya"},"songName":"Seishun Oden (Reloaded Ver.)","type":2,"typeNumber":1,"annId":20193,"annSongId":19836,"highRisk":0,"animeScore":"6.7","animeType":"special","vintage":"Winter 2018","animeDifficulty":23.428507215107647,"animeTags":["Super Power","Football"],"animeGenre":["Sports","Supernatural"],"altAnimeNames":["Inazuma Eleven: Reloaded"],"altAnimeNamesAnswers":[],"siteIds":{"annId":20193,"malId":37814,"kitsuId":41364,"aniListId":102933},"rebroadcast":0,"dub":0,"seasonInfo":{"name":"TV Special","number":"1.0"},"popularityRank":5256},"correctGuess":false,"wrongGuess":true,"answer":"SaiKano (20203ms)","correctCount":3,"wrongCount":5,"startPoint":22,"videoLength":84.218,"videoUrl":"https://nawdist.animemusicquiz.com/l28hva.webm","correctGuessPlayers":["Diukes","hubcioskubcio","Dry"],"listStates":[{"name":"hubcioskubcio","status":2,"score":0}]},{"songNumber":7,"songInfo":{"animeNames":{"english":"Masamune-kun's Revenge","romaji":"Masamune-kun no Revenge"},"artist":"ChouCho","composerInfo":{"groupId":80026164,"name":"AstroNoteS"},"arrangerInfo":{"groupId":80026164,"name":"AstroNoteS"},"songName":"Elemental World","type":2,"typeNumber":1,"annId":18749,"annSongId":16272,"highRisk":0,"animeScore":"6.5","animeType":"TV","vintage":"Winter 2017","animeDifficulty":29.51487551184557,"animeTags":["School","Shounen","Male Protagonist","Primarily Female Cast","Love Triangle","Tsundere","Fitness","Bullying","Revenge","Kuudere","Ojou-sama","Heterosexual"],"animeGenre":["Comedy","Romance","Slice of Life"],"altAnimeNames":["Masamune-kun no Revenge","Masamune-kun's Revenge"],"altAnimeNamesAnswers":[],"siteIds":{"annId":18749,"malId":33487,"kitsuId":12267,"aniListId":21857},"rebroadcast":0,"dub":0,"seasonInfo":{"name":"Season","number":"1.0"},"popularityRank":230},"correctGuess":true,"wrongGuess":false,"answer":"Masamune-kun no Revenge (7850ms)","correctCount":6,"wrongCount":2,"startPoint":12,"videoLength":89.513,"videoUrl":"https://nawdist.animemusicquiz.com/xdfd3r.webm","correctGuessPlayers":["Diukes","Swapin","Dry","inta","tmokenc","xeyz"],"listStates":[{"name":"Diukes","status":2,"score":0},{"name":"Swapin","status":2,"score":10},{"name":"Dry","status":2,"score":4},{"name":"inta","status":2,"score":5},{"name":"tmokenc","status":2,"score":6},{"name":"xeyz","status":2,"score":6}]},{"songNumber":8,"songInfo":{"animeNames":{"english":"Hakusai Anime","romaji":"Hakusai Anime"},"artist":"Lon","composerInfo":{"artistId":18252,"name":"LamazeP"},"arrangerInfo":{"artistId":18252,"name":"LamazeP"},"songName":"Hakusai","type":2,"typeNumber":1,"annId":24582,"annSongId":34542,"highRisk":0,"animeScore":"4.2","animeType":"ONA","vintage":"Summer 2013","animeDifficulty":24.23590140964674,"animeTags":["School","Slapstick","Primarily Female Cast","Female Protagonist","Teacher","Flash"],"animeGenre":["Comedy","Romance","Slice of Life"],"altAnimeNames":["Hakusai Anime"],"altAnimeNamesAnswers":[],"siteIds":{"annId":24582,"malId":19495,"kitsuId":9839,"aniListId":19495},"rebroadcast":0,"dub":0,"seasonInfo":null,"popularityRank":8557},"correctGuess":false,"wrongGuess":true,"answer":"","correctCount":2,"wrongCount":6,"startPoint":48,"videoLength":90.114,"videoUrl":"https://nawdist.animemusicquiz.com/beafl5.webm","correctGuessPlayers":["Diukes","Swapin"],"listStates":[{"name":"Swapin","status":2,"score":5}]},{"songNumber":9,"songInfo":{"animeNames":{"english":"Cybernetics Guardian","romaji":"Seijuki Cyguard"},"artist":"TRASH GANG","composerInfo":{"groupId":80023711,"name":"Katsuya Satou & Yoshimi Sugimoto"},"arrangerInfo":{"groupId":80027334,"name":"TRASH GANG"},"songName":"CAN'T GET IT ENOUGH","type":2,"typeNumber":1,"annId":568,"annSongId":28299,"highRisk":0,"animeScore":"5.2","animeType":"OVA","vintage":"Fall 1989","animeDifficulty":23.305803571428573,"animeTags":["Demons","Male Protagonist","Primarily Male Cast","Gore","Henshin","Politics","Cyberpunk","Primarily Adult Cast","Guns","Dystopian","Fugitive","Cult","Urban","Cyborg","Heterosexual"],"animeGenre":["Mecha","Sci-Fi","Supernatural"],"altAnimeNames":["Seijuki Cyguard","Cybernetics Guardian"],"altAnimeNamesAnswers":[],"siteIds":{"annId":568,"malId":3882,"kitsuId":3322,"aniListId":3882},"rebroadcast":0,"dub":0,"seasonInfo":null,"popularityRank":5952},"correctGuess":false,"wrongGuess":true,"answer":"","correctCount":1,"wrongCount":7,"startPoint":46,"videoLength":214.013,"videoUrl":"https://nawdist.animemusicquiz.com/41nwsb.webm","correctGuessPlayers":["Dry"],"listStates":[{"name":"Dry","status":2,"score":3}]},{"songNumber":10,"songInfo":{"animeNames":{"english":"Hundred","romaji":"Hundred"},"artist":"M・A・O & Rika Kinugawa & Yui Makino","composerInfo":{"artistId":11629,"name":"Shuuhei Naruse"},"arrangerInfo":{"artistId":11629,"name":"Shuuhei Naruse"},"songName":"TABOOLESS","type":2,"typeNumber":2,"annId":17063,"annSongId":15259,"highRisk":0,"animeScore":"5.9","animeType":"TV","vintage":"Spring 2016","animeDifficulty":20.08127533783784,"animeTags":["Female Harem","Swordplay","School","Male Protagonist","Crossdressing","Philosophy","Cosmic Horror","Cannibalism","Heterosexual"],"animeGenre":["Action","Ecchi","Mecha","Sci-Fi"],"altAnimeNames":["Hundred"],"altAnimeNamesAnswers":[],"siteIds":{"annId":17063,"malId":31338,"kitsuId":11029,"aniListId":21362},"rebroadcast":0,"dub":0,"seasonInfo":null,"popularityRank":868},"correctGuess":true,"wrongGuess":false,"answer":"hundred (5245ms)","correctCount":5,"wrongCount":3,"startPoint":67,"videoLength":89.645,"videoUrl":"https://nawdist.animemusicquiz.com/fg21h1meryp41gaq.webm","correctGuessPlayers":["Diukes","Swapin","Dry","inta","tmokenc"],"listStates":[{"name":"Diukes","status":2,"score":0},{"name":"Swapin","status":2,"score":7},{"name":"Dry","status":2,"score":2},{"name":"inta","status":2,"score":5},{"name":"xeyz","status":2,"score":3}]},{"songNumber":11,"songInfo":{"animeNames":{"english":"Star☆Twinkle Precure","romaji":"Star☆Twinkle Precure"},"artist":"Chihaya Yoshitake","composerInfo":{"artistId":12139,"name":"Shinji Tamura"},"arrangerInfo":{"groupId":80024361,"name":"Yoshihiro Kusano & Shinji Tamura"},"songName":"Papepipu☆Romantic","type":2,"typeNumber":1,"annId":21719,"annSongId":23398,"highRisk":0,"animeScore":"7.5","animeType":"TV","vintage":"Winter 2019","animeDifficulty":31.96366213500656,"animeTags":["Kids","Magic","Police","Swordplay","School","Space","Super Power","Primarily Female Cast","Cute Girls Doing Cute Things","Female Protagonist","Henshin","Ensemble Cast","Mafia","Nekomimi","Guns","Super Robot","Superhero","Robots","Aliens","Episodic","Dragons","Archery","Revenge","Kemonomimi","Urban Fantasy","Primarily Child Cast","Tokusatsu","Language Barrier","Artificial Intelligence","Astronomy","Shapeshifting","Ojou-sama","Spearplay","Anthropomorphism","Travel","Filmmaking"],"animeGenre":["Adventure","Fantasy","Mahou Shoujo","Sci-Fi"],"altAnimeNames":["Star☆Twinkle Precure"],"altAnimeNamesAnswers":[],"siteIds":{"annId":21719,"malId":38578,"kitsuId":42019,"aniListId":105857},"rebroadcast":0,"dub":0,"seasonInfo":{"name":"Season","number":"2019"},"popularityRank":4093},"correctGuess":false,"wrongGuess":true,"answer":"","correctCount":1,"wrongCount":7,"startPoint":19,"videoLength":89.061,"videoUrl":"https://nawdist.animemusicquiz.com/h1odqu.webm","correctGuessPlayers":["tmokenc"],"listStates":[{"name":"tmokenc","status":1,"score":0},{"name":"xeyz","status":2,"score":10}]},{"songNumber":12,"songInfo":{"animeNames":{"english":"The Garden of Sinners: Recalled Out Summer","romaji":"Kara no Kyoukai: Mirai Fukuin"},"artist":"Kalafina","composerInfo":{"artistId":3019,"name":"Yuki Kajiura"},"arrangerInfo":{"artistId":3019,"name":"Yuki Kajiura"},"songName":"Allelujah","type":2,"typeNumber":1,"annId":15249,"annSongId":13269,"highRisk":0,"animeScore":"7.8","animeType":"movie","vintage":"Summer 2013","animeDifficulty":24.17144569174757,"animeTags":["Super Power","Female Protagonist","Primarily Adult Cast","Time Skip","Achronological Order","Terrorism","Urban Fantasy","Urban","Crime"],"animeGenre":["Drama","Mystery","Supernatural"],"altAnimeNames":["Kara no Kyoukai: Mirai Fukuin","The Garden of Sinners: Recalled Out Summer"],"altAnimeNamesAnswers":[],"siteIds":{"annId":15249,"malId":14807,"kitsuId":7167,"aniListId":14807},"rebroadcast":0,"dub":0,"seasonInfo":{"name":"Movie","number":"2013"},"popularityRank":1828},"correctGuess":true,"wrongGuess":false,"answer":"Kara no Kyoukai: Mirai Fukuin (20183ms)","correctCount":4,"wrongCount":4,"startPoint":252,"videoLength":294.448,"videoUrl":"https://nawdist.animemusicquiz.com/i1nh0d.webm","correctGuessPlayers":["Diukes","Dry","inta","xeyz"],"listStates":[{"name":"Dry","status":2,"score":5},{"name":"xeyz","status":2,"score":8}]},{"songNumber":13,"songInfo":{"animeNames":{"english":"Carnival Phantasm","romaji":"Carnival Phantasm"},"artist":"Masaaki Endoh","composerInfo":{"artistId":12826,"name":"KATE"},"arrangerInfo":{"artistId":10424,"name":"Katsuhiko Kurosu"},"songName":"Fellows","type":2,"typeNumber":1,"annId":12270,"annSongId":11304,"highRisk":0,"animeScore":"7.7","animeType":"OVA","vintage":"Summer 2011","animeDifficulty":38.3780856092437,"animeTags":["Female Harem","Magic","Parody","Vampire","Slapstick","Ensemble Cast","Nekomimi","Meta","Crossover","Bar","Mythology","Slavery","Maids","Surreal Comedy","Samurai","Urban Fantasy","Urban","Kuudere","Spearplay"],"animeGenre":["Comedy","Supernatural"],"altAnimeNames":["Carnival Phantasm"],"altAnimeNamesAnswers":["Carnival Phantasm"],"siteIds":{"annId":12270,"malId":10012,"kitsuId":5992,"aniListId":10012},"rebroadcast":0,"dub":0,"seasonInfo":{"name":"OVA","number":"1.0"},"popularityRank":1197},"correctGuess":false,"wrongGuess":true,"answer":"Baka to Test to Shoukanjuu (15362ms)","correctCount":3,"wrongCount":5,"startPoint":63,"videoLength":88.929,"videoUrl":"https://nawdist.animemusicquiz.com/klr8y5.webm","correctGuessPlayers":["Diukes","Dry","xeyz"],"listStates":[{"name":"Diukes","status":2,"score":6},{"name":"Dry","status":2,"score":8},{"name":"xeyz","status":2,"score":10}]},{"songNumber":14,"songInfo":{"animeNames":{"english":"Uma Musume: Pretty Derby Season 3","romaji":"Uma Musume: Pretty Derby Season 3"},"artist":"Hinaki Yano","composerInfo":{"artistId":15912,"name":"Atsuhito Satou"},"arrangerInfo":{"artistId":15912,"name":"Atsuhito Satou"},"songName":"Sora no Hohoemikata","type":2,"typeNumber":3,"annId":26547,"annSongId":41525,"highRisk":0,"animeScore":"7.8","animeType":"TV","vintage":"Fall 2023","animeDifficulty":24.765634964923468,"animeTags":["School","Yuri","Primarily Female Cast","CGI","Female Protagonist","Idol","Maids","Kemonomimi","Athletics","Animals","Urban","Primarily Teen Cast"],"animeGenre":["Drama","Slice of Life","Sports"],"altAnimeNames":["Uma Musume: Pretty Derby Season 3"],"altAnimeNamesAnswers":[],"siteIds":{"annId":26547,"malId":53526,"kitsuId":46711,"aniListId":156632},"rebroadcast":0,"dub":0,"seasonInfo":{"name":"Season","number":"3.0"},"popularityRank":2316},"correctGuess":true,"wrongGuess":false,"answer":"Uma Musume: Pretty Derby Season 3 (9326ms)","correctCount":5,"wrongCount":3,"startPoint":151,"videoLength":239.288,"videoUrl":"https://nawdist.animemusicquiz.com/u3ofir.webm","correctGuessPlayers":["Diukes","Swapin","inta","tmokenc","xeyz"],"listStates":[{"name":"inta","status":2,"score":8},{"name":"tmokenc","status":2,"score":4},{"name":"xeyz","status":2,"score":8}]},{"songNumber":15,"songInfo":{"animeNames":{"english":"KamiErabi GOD.app","romaji":"KamiErabi GOD.app"},"artist":"LEEVELLES","composerInfo":{"groupId":19436,"name":"LEEVELLES"},"arrangerInfo":{"groupId":80026251,"name":"Shogo Ohnishi & LEEVELLES"},"songName":"Koufuku no Susume","type":2,"typeNumber":1,"annId":31078,"annSongId":43900,"highRisk":0,"animeScore":"6.0","animeType":"TV","vintage":"Fall 2024","animeDifficulty":25.96438125,"animeTags":["Full CGI","Gods"],"animeGenre":["Action","Drama","Psychological","Supernatural"],"altAnimeNames":["KamiErabi GOD.app"],"altAnimeNamesAnswers":[],"siteIds":{"annId":31078,"malId":56967,"kitsuId":48398,"aniListId":172199},"rebroadcast":0,"dub":0,"seasonInfo":{"name":"Season","number":"2.0"},"popularityRank":5200},"correctGuess":true,"wrongGuess":false,"answer":"KamiErabi GOD.app (2364ms)","correctCount":1,"wrongCount":7,"startPoint":51,"videoLength":88.303,"videoUrl":"https://nawdist.animemusicquiz.com/h9xfcz.webm","correctGuessPlayers":["inta"],"listStates":[{"name":"inta","status":1,"score":1}]},{"songNumber":16,"songInfo":{"animeNames":{"english":"Peach Boy Riverside","romaji":"Peach Boy Riverside"},"artist":"Mitei no Hanashi","composerInfo":{"artistId":22346,"name":"Aru."},"arrangerInfo":{"artistId":16344,"name":"The Cheshire"},"songName":"Yoru o Koeru Ashioto","type":2,"typeNumber":1,"annId":23550,"annSongId":34289,"highRisk":0,"animeScore":"6.0","animeType":"TV","vintage":"Summer 2021","animeDifficulty":17.034389555350952,"animeTags":["Demons","Shounen","Male Protagonist","Gore","Female Protagonist","Achronological Order","Yandere","Crossdressing","Mythology","Kemonomimi","Monster Girl","Heterosexual","Travel"],"animeGenre":["Adventure","Fantasy"],"altAnimeNames":["Peach Boy Riverside"],"altAnimeNamesAnswers":[],"siteIds":{"annId":23550,"malId":42627,"kitsuId":43870,"aniListId":122441},"rebroadcast":0,"dub":0,"seasonInfo":null,"popularityRank":1155},"correctGuess":false,"wrongGuess":true,"answer":"Boku no Hero Academia (14112ms)","correctCount":2,"wrongCount":6,"startPoint":38,"videoLength":90.02,"videoUrl":"https://nawdist.animemusicquiz.com/ttaach.webm","correctGuessPlayers":["Dry","tmokenc"],"listStates":[{"name":"Dry","status":2,"score":4},{"name":"tmokenc","status":2,"score":7}]},{"songNumber":17,"songInfo":{"animeNames":{"english":"Back Street Girls: Gokudols","romaji":"Back Street Girls: Gokudols"},"artist":"Gokudols Otoko-gumi","composerInfo":{"artistId":14582,"name":"CHI-MEY"},"arrangerInfo":{"artistId":14582,"name":"CHI-MEY"},"songName":"Hoshi no Katachi","type":2,"typeNumber":2,"annId":20851,"annSongId":21484,"highRisk":0,"animeScore":"6.6","animeType":"TV","vintage":"Summer 2018","animeDifficulty":28.04311129708652,"animeTags":["Seinen","Gender Bending","Slapstick","Primarily Female Cast","Primarily Male Cast","Otaku Culture","Primarily Adult Cast","Idol","Crossdressing","Yakuza","Surreal Comedy","Urban","Body Horror","Transgender"],"animeGenre":["Comedy","Ecchi","Music"],"altAnimeNames":["Back Street Girls: Gokudols"],"altAnimeNamesAnswers":[],"siteIds":{"annId":20851,"malId":36873,"kitsuId":41021,"aniListId":100665},"rebroadcast":0,"dub":0,"seasonInfo":null,"popularityRank":1521},"correctGuess":false,"wrongGuess":true,"answer":"gg    (20178ms)","correctCount":4,"wrongCount":4,"startPoint":38,"videoLength":89.728,"videoUrl":"https://nawdist.animemusicquiz.com/jq8c14.webm","correctGuessPlayers":["Diukes","Swapin","2skr","Dry"],"listStates":[{"name":"Swapin","status":2,"score":8},{"name":"2skr","status":2,"score":8}]},{"songNumber":18,"songInfo":{"animeNames":{"english":"Inferius Wakusei Senshi Gaiden Condition Green","romaji":"Inferius Wakusei Senshi Gaiden Condition Green"},"artist":"Yumi Hikita","composerInfo":{"artistId":11398,"name":"Kazuhiko Izu"},"arrangerInfo":{"artistId":11398,"name":"Kazuhiko Izu"},"songName":"Ai o Subete (English Version)","type":2,"typeNumber":3,"annId":3323,"annSongId":5767,"highRisk":0,"animeScore":"4.8","animeType":"OVA","vintage":"Fall 1991","animeDifficulty":18.278702905167748,"animeTags":["Magic","Military","Super Power","War","Aliens"],"animeGenre":["Action","Fantasy","Sci-Fi"],"altAnimeNames":["Inferius Wakusei Senshi Gaiden Condition Green"],"altAnimeNamesAnswers":[],"siteIds":{"annId":3323,"malId":16259,"kitsuId":7398,"aniListId":16259},"rebroadcast":0,"dub":0,"seasonInfo":null,"popularityRank":7993},"correctGuess":false,"wrongGuess":true,"answer":"","correctCount":0,"wrongCount":8,"startPoint":39,"videoLength":70.042,"videoUrl":"https://nawdist.animemusicquiz.com/7bwatb.webm","correctGuessPlayers":[],"listStates":[{"name":"Diukes","status":2,"score":5}]},{"songNumber":19,"songInfo":{"animeNames":{"english":"Ascendance of a Bookworm","romaji":"Honzuki no Gekokujou: Shisho ni Naru Tame ni wa Shudan o Erandeiraremasen"},"artist":"Maaya Sakamoto","composerInfo":{"artistId":261,"name":"Maaya Sakamoto"},"arrangerInfo":{"artistId":484,"name":"h-wonder"},"songName":"Kotoba ni Dekinai","type":2,"typeNumber":1,"annId":24606,"annSongId":36446,"highRisk":0,"animeScore":"7.9","animeType":"TV","vintage":"Spring 2022","animeDifficulty":28.61967433249896,"animeTags":["Historical","Magic","Female Protagonist","Politics","Work","Reincarnation","Isekai","Economics","Age Regression","Adoption","Religion","Found Family","Orphan","Class Struggle","Medieval"],"animeGenre":["Drama","Fantasy","Slice of Life"],"altAnimeNames":["Honzuki no Gekokujou: Shisho ni Naru Tame ni wa Shudan o Erandeiraremasen","Ascendance of a Bookworm"],"altAnimeNamesAnswers":[],"siteIds":{"annId":24606,"malId":42429,"kitsuId":43607,"aniListId":121176},"rebroadcast":0,"dub":0,"seasonInfo":{"name":"Season","number":"3.0"},"popularityRank":1287},"correctGuess":false,"wrongGuess":true,"answer":"Botan Kamiina Fully Blossoms When Drunk (15537ms)","correctCount":5,"wrongCount":3,"startPoint":20,"videoLength":88.644,"videoUrl":"https://nawdist.animemusicquiz.com/7xgi9l.webm","correctGuessPlayers":["Diukes","hubcioskubcio","Dry","tmokenc","xeyz"],"listStates":[{"name":"hubcioskubcio","status":2,"score":0},{"name":"Dry","status":2,"score":6},{"name":"tmokenc","status":2,"score":9},{"name":"xeyz","status":2,"score":8}]},{"songNumber":20,"songInfo":{"animeNames":{"english":"Sound! Euphonium: Ensemble Contest Arc","romaji":"Gekijouban Hibike! Euphonium: Ensemble Contest-hen"},"artist":"TRUE","composerInfo":{"artistId":12801,"name":"Takuya Watanabe"},"arrangerInfo":{"artistId":12801,"name":"Takuya Watanabe"},"songName":"Ensemble","type":2,"typeNumber":1,"annId":25753,"annSongId":40778,"highRisk":0,"animeScore":"7.8","animeType":"OVA","vintage":"Summer 2023","animeDifficulty":29.351813122234518,"animeTags":["School","School Club","Primarily Female Cast","Female Protagonist","Coming of Age","Ensemble Cast","Band","Primarily Teen Cast","Classical Music"],"animeGenre":["Drama","Music","Slice of Life"],"altAnimeNames":["Gekijouban Hibike! Euphonium: Ensemble Contest-hen","Sound! Euphonium: Ensemble Contest Arc"],"altAnimeNamesAnswers":[],"siteIds":{"annId":25753,"malId":51995,"kitsuId":46158,"aniListId":150429},"rebroadcast":0,"dub":0,"seasonInfo":{"name":"OVA","number":"2023"},"popularityRank":2718},"correctGuess":false,"wrongGuess":true,"answer":"Eiga Precure All Stars DX2: Kibou no Hikari☆Rainbow Jewel o Mamore! (15103ms)","correctCount":3,"wrongCount":5,"startPoint":254,"videoLength":282.54,"videoUrl":"https://nawdist.animemusicquiz.com/onw6la.webm","correctGuessPlayers":["Swapin","2skr","tmokenc"],"listStates":[{"name":"tmokenc","status":2,"score":8},{"name":"xeyz","status":2,"score":9}]}]}