{"roomName":"tour","startTime":"Sun Feb 01 2026 17:07:06 GMT+0100","songs":[{"songNumber":1,"songInfo":{"animeNames":{"english":"Fate/kaleid liner Prisma☆Illya 3rei!!","romaji":"Fate/kaleid liner Prisma☆Illya 3rei!!"},"artist":"ChouCho","composerInfo":{"groupId":80026164,"name":"AstroNoteS"},"arrangerInfo":{"groupId":80026164,"name":"AstroNoteS"},"songName":"Asterism","type":1,"typeNumber":1,"annId":17690,"highRisk":0,"animeScore":"7.3","animeType":"TV","vintage":"Summer 2016","animeDifficulty":37.905115650207776,"animeTags":["Magic","Swordplay","Shounen","Primarily Female Cast","Cute Girls Doing Cute Things","Post-Apocalyptic","Female Protagonist","Henshin","Nudity","Alternate Universe","Isekai","Maids","Archery","Urban Fantasy","Assassins","Tanned Skin","Primarily Child Cast","Urban","Ojou-sama","Spearplay","Anthropomorphism"],"animeGenre":["Action","Comedy","Ecchi","Fantasy","Mahou Shoujo"],"altAnimeNames":["Fate/kaleid liner Prisma☆Illya 3rei!!"],"altAnimeNamesAnswers":[],"siteIds":{"annId":17690,"malId":31706,"kitsuId":11438,"aniListId":21379},"rebroadcast":0,"dub":0,"seasonInfo":{"name":"Season","number":"4.0"}},"correctGuess":true,"wrongGuess":false,"answer":"Fate&#x2F;kaleid liner Prisma☆Illya 3rei!!","correctCount":5,"wrongCount":3,"startPoint":24,"videoLength":88.609,"videoUrl":"https://eudist.animemusicquiz.com/kj41e7.webm","correctGuessPlayers":["gabussy","Dry","MahiruShiina","SAVAGEGENIUS","Bommie"],"listStates":[{"name":"Dry","status":2,"score":4},{"name":"MahiruShiina","status":2,"score":8},{"name":"Bommie","status":2,"score":8}]},{"songNumber":2,"songInfo":{"animeNames":{"english":"The Dungeon of Black Company","romaji":"Meikyuu Black Company"},"artist":"Humbreaders","composerInfo":{"groupId":8243,"name":"Humbreaders"},"arrangerInfo":{"groupId":80026953,"name":"Humbreaders & Uki"},"songName":"World Is Mine","type":2,"typeNumber":1,"annId":23981,"highRisk":0,"animeScore":"7.0","animeType":"TV","vintage":"Summer 2021","animeDifficulty":26.94738225151172,"animeTags":["Demons","Magic","Parody","Satire","Male Protagonist","Post-Apocalyptic","Anti-Hero","Work","Alternate Universe","Time Skip","Isekai","Slavery","Economics","Revenge","Dungeon","Villainess"],"animeGenre":["Comedy","Fantasy"],"altAnimeNames":["Meikyuu Black Company","The Dungeon of Black Company"],"altAnimeNamesAnswers":[],"siteIds":{"annId":23981,"malId":42340,"kitsuId":43268,"aniListId":120608},"rebroadcast":0,"dub":0,"seasonInfo":null},"correctGuess":true,"wrongGuess":false,"answer":"Meikyuu Black Company","correctCount":5,"wrongCount":3,"startPoint":39,"videoLength":89.019,"videoUrl":"https://eudist.animemusicquiz.com/2607go.webm","correctGuessPlayers":["Dry","JustaWeirdo","MahiruShiina","SAVAGEGENIUS","Bommie"],"listStates":[{"name":"Dry","status":2,"score":5},{"name":"JustaWeirdo","status":2,"score":6},{"name":"Bommie","status":2,"score":6}]},{"songNumber":3,"songInfo":{"animeNames":{"english":"Beast Tamer","romaji":"Yuusha Party o Tsuihou sareta Beast Tamer, Saikyoushu no Nekomimi Shoujo to Deau"},"artist":"MADKID","composerInfo":{"artistId":12793,"name":"Morihiro Suzuki"},"arrangerInfo":{"artistId":15177,"name":"TAKT"},"songName":"Change The World","type":1,"typeNumber":1,"annId":25786,"highRisk":0,"animeScore":"6.8","animeType":"TV","vintage":"Fall 2022","animeDifficulty":37.32797206362153,"animeTags":["Female Harem","Magic","Male Protagonist","Primarily Female Cast","Cute Girls Doing Cute Things","Nekomimi","Dragons","Kemonomimi","Monster Girl","Animals","Twins","Heterosexual","Found Family","Orphan","Fairy","Creature Taming"],"animeGenre":["Adventure","Fantasy"],"altAnimeNames":["Beast Tamer","Yuusha Party o Tsuihou sareta Beast Tamer, Saikyoushu no Nekomimi Shoujo to Deau"],"altAnimeNamesAnswers":[],"siteIds":{"annId":25786,"malId":52046,"kitsuId":46171,"aniListId":150695},"rebroadcast":0,"dub":0,"seasonInfo":null},"correctGuess":false,"wrongGuess":true,"answer":"Bleach: Sennen Kessen-hen","correctCount":5,"wrongCount":3,"startPoint":57,"videoLength":88.81,"videoUrl":"https://eudist.animemusicquiz.com/1h2va8.webm","correctGuessPlayers":["gabussy","JustaWeirdo","MahiruShiina","SAVAGEGENIUS","Bommie"],"listStates":[{"name":"gabussy","status":2,"score":null},{"name":"MahiruShiina","status":2,"score":7},{"name":"Bommie","status":2,"score":6}]},{"songNumber":4,"songInfo":{"animeNames":{"english":"Pokémon 3: The Movie","romaji":"Pocket Monsters: Kesshoutou no Teiou Entei"},"artist":"Rica Matsumoto","composerInfo":{"artistId":2483,"name":"Hirokazu Tanaka"},"arrangerInfo":{"artistId":2483,"name":"Hirokazu Tanaka"},"songName":"OK! 2000","type":1,"typeNumber":1,"annId":831,"highRisk":0,"animeScore":"6.8","animeType":"movie","vintage":"Summer 2000","animeDifficulty":24.530731811329737,"animeTags":["Kids","Male Protagonist","Family Life","Rural","Animals","Creature Taming"],"animeGenre":["Action","Adventure","Drama","Fantasy"],"altAnimeNames":["Pocket Monsters: Kesshoutou no Teiou Entei","Pokémon 3: The Movie","Pokémon: Spell of the Unown"],"altAnimeNamesAnswers":["Pocket Monsters","Pokémon","Pocket Monsters: Advanced Generation","Pokémon: Advanced","Pokémon: Battle Frontier","Pocket Monsters: Mewtwo! Ware wa Koko ni Ari","Pokémon: Mewtwo Returns"],"siteIds":{"annId":831,"malId":1118,"kitsuId":1002,"aniListId":1118},"rebroadcast":0,"dub":0,"seasonInfo":{"name":"Movie","number":"3.0"}},"correctGuess":true,"wrongGuess":false,"answer":"Pocket Monsters: Kesshoutou no Teiou Entei","correctCount":7,"wrongCount":1,"startPoint":52,"videoLength":199.833,"videoUrl":"https://eudist.animemusicquiz.com/mmgav5.webm","correctGuessPlayers":["gabussy","Dry","JustaWeirdo","MahiruShiina","SAVAGEGENIUS","Bommie","Floth"],"listStates":[{"name":"gabussy","status":2,"score":null},{"name":"Dry","status":2,"score":5},{"name":"JustaWeirdo","status":2,"score":7},{"name":"Bommie","status":2,"score":7}]},{"songNumber":5,"songInfo":{"animeNames":{"english":"Senki Zesshou Symphogear AXZ","romaji":"Senki Zesshou Symphogear AXZ"},"artist":"Nana Mizuki","composerInfo":{"artistId":10500,"name":"Noriyasu Agematsu"},"arrangerInfo":{"artistId":10496,"name":"Daisuke Kikuta"},"songName":"Gekka Bijin","type":3,"typeNumber":0,"annId":19724,"highRisk":0,"animeScore":"7.6","animeType":"TV","vintage":"Summer 2017","animeDifficulty":28.0898074028462,"animeTags":["Swordplay","Yuri","Tragedy","Primarily Female Cast","Female Protagonist","Henshin","Ensemble Cast","Idol","Aliens","Mythology","Gods","Philosophy","LGBTQ+ Themes","Drugs","Cult","Urban","Alchemy","Orphan"],"animeGenre":["Action","Drama","Mahou Shoujo","Music","Sci-Fi"],"altAnimeNames":["Senki Zesshou Symphogear AXZ"],"altAnimeNamesAnswers":[],"siteIds":{"annId":19724,"malId":32836,"kitsuId":11883,"aniListId":21672},"rebroadcast":0,"dub":0,"seasonInfo":{"name":"Season","number":"4.0"}},"correctGuess":true,"wrongGuess":false,"answer":"Senki Zesshou Symphogear AXZ","correctCount":3,"wrongCount":5,"startPoint":58,"videoLength":109.309,"videoUrl":"https://eudist.animemusicquiz.com/5vu7d4.webm","correctGuessPlayers":["Dry","MahiruShiina","Floth"],"listStates":[{"name":"gabussy","status":2,"score":null},{"name":"MahiruShiina","status":2,"score":6},{"name":"HaruUrara","status":2,"score":8}]},{"songNumber":6,"songInfo":{"animeNames":{"english":"Lapis Re:LiGHTs","romaji":"Lapis Re:LiGHTs"},"artist":"Konohana wa Otome","composerInfo":{"groupId":80023363,"name":"Kurio & Takashige Tsukada"},"arrangerInfo":{"artistId":15451,"name":"Takashige Tsukada"},"songName":"Inochi Mijikashi, Ryouran Otome","type":3,"typeNumber":0,"annId":22935,"highRisk":0,"animeScore":"6.3","animeType":"TV","vintage":"Summer 2020","animeDifficulty":26.926260544478527,"animeTags":["Magic","School","Yuri","Primarily Female Cast","Cute Girls Doing Cute Things","Female Protagonist","Ensemble Cast","Idol","Ghost","LGBTQ+ Themes","Ojou-sama","Primarily Teen Cast","Creature Taming"],"animeGenre":["Fantasy","Music"],"altAnimeNames":["Lapis Re:LiGHTs"],"altAnimeNamesAnswers":[],"siteIds":{"annId":22935,"malId":37587,"kitsuId":41115,"aniListId":104937},"rebroadcast":0,"dub":0,"seasonInfo":null},"correctGuess":false,"wrongGuess":true,"answer":"aiakts","correctCount":4,"wrongCount":4,"startPoint":14,"videoLength":60.318,"videoUrl":"https://eudist.animemusicquiz.com/nzp3oz.webm","correctGuessPlayers":["MahiruShiina","Bommie","Floth","HaruUrara"],"listStates":[{"name":"MahiruShiina","status":2,"score":8},{"name":"Bommie","status":2,"score":7},{"name":"HaruUrara","status":2,"score":9}]},{"songNumber":7,"songInfo":{"animeNames":{"english":"Symphogear","romaji":"Senki Zesshou Symphogear"},"artist":"Ayahi Takagaki","composerInfo":{"artistId":10500,"name":"Noriyasu Agematsu"},"arrangerInfo":{"artistId":10501,"name":"Seima Iwahashi"},"songName":"Makyuu Ichaival","type":3,"typeNumber":0,"annId":13659,"highRisk":0,"animeScore":"6.8","animeType":"TV","vintage":"Winter 2012","animeDifficulty":34.47261036857027,"animeTags":["Military","Swordplay","School","Super Power","Yuri","Tragedy","Primarily Female Cast","Gore","Female Protagonist","Henshin","Idol","Guns","Tsundere","Superhero","Mythology","Dancing","Conspiracy","Urban","Primarily Teen Cast","Spearplay"],"animeGenre":["Action","Drama","Mahou Shoujo","Music","Sci-Fi"],"altAnimeNames":["Senki Zesshou Symphogear","Symphogear"],"altAnimeNamesAnswers":[],"siteIds":{"annId":13659,"malId":11751,"kitsuId":6587,"aniListId":11751},"rebroadcast":0,"dub":0,"seasonInfo":{"name":"Season","number":"1.0"}},"correctGuess":true,"wrongGuess":false,"answer":"Symphogear","correctCount":6,"wrongCount":2,"startPoint":54,"videoLength":141.426,"videoUrl":"https://eudist.animemusicquiz.com/9wh31f.webm","correctGuessPlayers":["gabussy","Dry","MahiruShiina","Bommie","Floth","HaruUrara"],"listStates":[{"name":"gabussy","status":2,"score":null},{"name":"Dry","status":2,"score":3},{"name":"MahiruShiina","status":2,"score":5},{"name":"Bommie","status":2,"score":5},{"name":"HaruUrara","status":2,"score":7}]},{"songNumber":8,"songInfo":{"animeNames":{"english":"Is It Wrong to Try to Pick Up Girls in a Dungeon? II","romaji":"Dungeon ni Deai o Motomeru no wa Machigatteiru Darou ka II"},"artist":"Haruka Chisuga","composerInfo":{"artistId":10467,"name":"Sonosuke Takao"},"arrangerInfo":{"artistId":15254,"name":"Yuta Yamaguchi"},"songName":"Tsuki no Shirabe","type":3,"typeNumber":0,"annId":20673,"highRisk":1,"animeScore":"7.1","animeType":"TV","vintage":"Summer 2019","animeDifficulty":21.04775015137753,"animeTags":["Female Harem","Magic","Swordplay","Male Protagonist","Primarily Female Cast","Nudity","Ensemble Cast","Mythology","Gods","Kemonomimi","Tanned Skin","Dungeon","Kuudere","Tomboy"],"animeGenre":["Action","Adventure","Comedy","Fantasy","Romance"],"altAnimeNames":["DanMachi II","Dungeon ni Deai o Motomeru no wa Machigatteiru Darou ka II","Is It Wrong to Try to Pick Up Girls in a Dungeon? II"],"altAnimeNamesAnswers":[],"siteIds":{"annId":20673,"malId":37347,"kitsuId":40599,"aniListId":101167},"rebroadcast":0,"dub":0,"seasonInfo":{"name":"Season","number":"2.0"}},"correctGuess":true,"wrongGuess":false,"answer":"DanMachi II","correctCount":5,"wrongCount":3,"startPoint":3,"videoLength":115.282,"videoUrl":"https://eudist.animemusicquiz.com/m5632h.webm","correctGuessPlayers":["gabussy","Dry","MahiruShiina","SAVAGEGENIUS","Bommie"],"listStates":[{"name":"gabussy","status":2,"score":null},{"name":"Dry","status":2,"score":5},{"name":"MahiruShiina","status":2,"score":6},{"name":"SAVAGEGENIUS","status":2,"score":null},{"name":"Bommie","status":2,"score":7}]},{"songNumber":9,"songInfo":{"animeNames":{"english":"Samurai Champloo","romaji":"Samurai Champloo"},"artist":"midicronica","composerInfo":{"artistId":23476,"name":"106"},"arrangerInfo":{"artistId":23476,"name":"106"},"songName":"san francisco","type":2,"typeNumber":5,"annId":2636,"highRisk":1,"animeScore":"8.4","animeType":"TV","vintage":"Spring 2004","animeDifficulty":32.94887506706009,"animeTags":["Historical","Martial Arts","Swordplay","Male Protagonist","Female Protagonist","Politics","Anti-Hero","Primarily Adult Cast","Shogi","Episodic","Pirates","Calligraphy","Rural","Ninja","Samurai","Assassins","Tanned Skin","Drugs","Anachronism","Kuudere","Heterosexual","Travel","Orphan","Hip-hop Music"],"animeGenre":["Action","Adventure","Comedy"],"altAnimeNames":["Samurai Champloo"],"altAnimeNamesAnswers":[],"siteIds":{"annId":2636,"malId":205,"kitsuId":181,"aniListId":205},"rebroadcast":0,"dub":0,"seasonInfo":null},"correctGuess":true,"wrongGuess":false,"answer":"Samurai Champloo","correctCount":2,"wrongCount":6,"startPoint":66,"videoLength":150.067,"videoUrl":"https://eudist.animemusicquiz.com/uf5buq.webm","correctGuessPlayers":["Dry","MahiruShiina"],"listStates":[{"name":"Dry","status":2,"score":7}]},{"songNumber":10,"songInfo":{"animeNames":{"english":"Tari Tari","romaji":"Tari Tari"},"artist":"Asami Seto","composerInfo":{"artistId":10700,"name":"Shirou Hamaguchi"},"arrangerInfo":{"artistId":10700,"name":"Shirou Hamaguchi"},"songName":"goin' my way!!","type":3,"typeNumber":0,"annId":14167,"highRisk":0,"animeScore":"7.2","animeType":"TV","vintage":"Summer 2012","animeDifficulty":21.934103057715312,"animeTags":["School","School Club","Family Life","Coming of Age","Ensemble Cast","Band","Animals","Coastal"],"animeGenre":["Music","Slice of Life"],"altAnimeNames":["Tari Tari"],"altAnimeNamesAnswers":[],"siteIds":{"annId":14167,"malId":13333,"kitsuId":6941,"aniListId":13333},"rebroadcast":0,"dub":0,"seasonInfo":null},"correctGuess":true,"wrongGuess":false,"answer":"Tari Tari","correctCount":1,"wrongCount":7,"startPoint":32,"videoLength":63.176,"videoUrl":"https://eudist.animemusicquiz.com/t9i4vt.webm","correctGuessPlayers":["Dry"],"listStates":[{"name":"Dry","status":2,"score":3}]},{"songNumber":11,"songInfo":{"animeNames":{"english":"Is It Wrong to Try to Pick Up Girls in a Dungeon?","romaji":"Dungeon ni Deai o Motomeru no wa Machigatteiru Darou ka"},"artist":"Maaya Uchida","composerInfo":{"artistId":20784,"name":"Rie"},"arrangerInfo":{"artistId":12327,"name":"Takeshi Watanabe"},"songName":"REALIZE ~Hajimari no Toki~","type":2,"typeNumber":2,"annId":16443,"highRisk":0,"animeScore":"7.3","animeType":"TV","vintage":"Spring 2015","animeDifficulty":21.65661656891496,"animeTags":["Female Harem","Magic","Swordplay","Male Protagonist","Primarily Female Cast","Nudity","Ensemble Cast","Love Triangle","Mythology","Gods","Cultivation","Elf","Dungeon","Kuudere","Medieval","Cohabitation"],"animeGenre":["Action","Adventure","Comedy","Fantasy","Romance"],"altAnimeNames":["DanMachi","Dungeon ni Deai o Motomeru no wa Machigatteiru Darou ka","Is It Wrong to Try to Pick Up Girls in a Dungeon?"],"altAnimeNamesAnswers":[],"siteIds":{"annId":16443,"malId":28121,"kitsuId":9962,"aniListId":20920},"rebroadcast":0,"dub":0,"seasonInfo":{"name":"Season","number":"1.0"}},"correctGuess":false,"wrongGuess":true,"answer":"my list","correctCount":2,"wrongCount":6,"startPoint":85,"videoLength":180.784,"videoUrl":"https://eudist.animemusicquiz.com/jpmrgk.webm","correctGuessPlayers":["gabussy","MahiruShiina"],"listStates":[{"name":"gabussy","status":2,"score":null},{"name":"Dry","status":2,"score":5},{"name":"MahiruShiina","status":2,"score":6},{"name":"SAVAGEGENIUS","status":2,"score":null},{"name":"Bommie","status":2,"score":7},{"name":"Floth","status":2,"score":4}]},{"songNumber":12,"songInfo":{"animeNames":{"english":"Non Non Biyori Repeat","romaji":"Non Non Biyori Repeat"},"artist":"Kotori Koiwai, Rie Murakawa, Ayane Sakura, Kana Asumi","composerInfo":{"artistId":5277,"name":"ZAQ"},"arrangerInfo":{"artistId":12206,"name":"Akito Matsuda"},"songName":"Okaeri","type":2,"typeNumber":1,"annId":16655,"highRisk":0,"animeScore":"8.1","animeType":"TV","vintage":"Summer 2015","animeDifficulty":30.149550398768163,"animeTags":["School","Seinen","Iyashikei","Primarily Female Cast","Cute Girls Doing Cute Things","Female Protagonist","Ensemble Cast","Achronological Order","Episodic","Rural","Primarily Child Cast","Kuudere","Tomboy"],"animeGenre":["Slice of Life"],"altAnimeNames":["Non Non Biyori Repeat"],"altAnimeNamesAnswers":[],"siteIds":{"annId":16655,"malId":23623,"kitsuId":8410,"aniListId":20694},"rebroadcast":0,"dub":0,"seasonInfo":{"name":"Season","number":"2.0"}},"correctGuess":true,"wrongGuess":false,"answer":"Non Non Biyori Repeat","correctCount":4,"wrongCount":4,"startPoint":60,"videoLength":94.517,"videoUrl":"https://eudist.animemusicquiz.com/me1l4j.webm","correctGuessPlayers":["gabussy","Dry","MahiruShiina","SAVAGEGENIUS"],"listStates":[{"name":"Dry","status":2,"score":8},{"name":"MahiruShiina","status":2,"score":8},{"name":"Bommie","status":2,"score":7}]},{"songNumber":13,"songInfo":{"animeNames":{"english":"10 Tokyo Warriors","romaji":"Tokyo Juushouden"},"artist":"Dera☆Sentimental","composerInfo":{"artistId":11892,"name":"The Yarari"},"arrangerInfo":{"groupId":80027740,"name":"Dera☆Sentimental"},"songName":"Dera Dera☆Shuffle","type":2,"typeNumber":5,"annId":1600,"highRisk":0,"animeScore":"4.3","animeType":"OVA","vintage":"Summer 1999","animeDifficulty":25.14575403979701,"animeTags":[],"animeGenre":["Action","Adventure","Supernatural"],"altAnimeNames":["10 Tokyo Warriors","Tokyo Juushouden"],"altAnimeNamesAnswers":[],"siteIds":{"annId":1600,"malId":1052,"kitsuId":942,"aniListId":1052},"rebroadcast":0,"dub":0,"seasonInfo":null},"correctGuess":false,"wrongGuess":true,"answer":"Ninja Slayer","correctCount":1,"wrongCount":7,"startPoint":32,"videoLength":88.562,"videoUrl":"https://eudist.animemusicquiz.com/kco7yj.webm","correctGuessPlayers":["HaruUrara"],"listStates":[{"name":"HaruUrara","status":2,"score":2}]},{"songNumber":14,"songInfo":{"animeNames":{"english":"The Familiar of Zero: Rondo of Princesses","romaji":"Zero no Tsukaima: Princess no Rondo"},"artist":"ICHIKO","composerInfo":{"artistId":13154,"name":"Kosuke Makino"},"arrangerInfo":{"artistId":10834,"name":"Riki Arai"},"songName":"YOU'RE THE ONE","type":1,"typeNumber":1,"annId":9200,"highRisk":0,"animeScore":"6.9","animeType":"TV","vintage":"Summer 2008","animeDifficulty":39.9778255988024,"animeTags":["Female Harem","Magic","School","Male Protagonist","Tsundere","Isekai","LGBTQ+ Themes","Elf","Heterosexual"],"animeGenre":["Action","Adventure","Comedy","Ecchi","Fantasy","Romance"],"altAnimeNames":["The Familiar of Zero: Rondo of Princesses","Zero no Tsukaima: Princess no Rondo"],"altAnimeNamesAnswers":[],"siteIds":{"annId":9200,"malId":3712,"kitsuId":3209,"aniListId":3712},"rebroadcast":0,"dub":0,"seasonInfo":{"name":"Season","number":"3.0"}},"correctGuess":false,"wrongGuess":true,"answer":"The Familiar of Zero F","correctCount":5,"wrongCount":3,"startPoint":2,"videoLength":88.672,"videoUrl":"https://eudist.animemusicquiz.com/usyc8x.webm","correctGuessPlayers":["gabussy","MahiruShiina","SAVAGEGENIUS","Bommie","HaruUrara"],"listStates":[{"name":"Dry","status":2,"score":5},{"name":"MahiruShiina","status":2,"score":7},{"name":"SAVAGEGENIUS","status":2,"score":null},{"name":"Bommie","status":2,"score":8},{"name":"HaruUrara","status":2,"score":7}]},{"songNumber":15,"songInfo":{"animeNames":{"english":"The Too-Perfect Saint: Tossed Aside by My Fiancé and Sold To Another Kingdom","romaji":"Kanpeki Sugite Kawaige ga Nai to Konyaku Haki Sareta Seijo wa Ringoku ni Urareru"},"artist":"WON","composerInfo":{"artistId":15318,"name":"TAKU INOUE"},"arrangerInfo":{"artistId":15318,"name":"TAKU INOUE"},"songName":"Sister","type":2,"typeNumber":1,"annId":33787,"highRisk":0,"animeScore":"7.1","animeType":"TV","vintage":"Spring 2025","animeDifficulty":28.45767230636503,"animeTags":["Demons","Magic","Shoujo","Tragedy","Female Protagonist","Revenge","Kuudere","Heterosexual","Royal Affairs"],"animeGenre":["Fantasy","Romance"],"altAnimeNames":["Kanpeki Sugite Kawaige ga Nai to Konyaku Haki Sareta Seijo wa Ringoku ni Urareru","Kanpekiseijo","The Too-Perfect Saint: Tossed Aside by My Fiancé and Sold To Another Kingdom"],"altAnimeNamesAnswers":[],"siteIds":{"annId":33787,"malId":60157,"kitsuId":49298,"aniListId":183275},"rebroadcast":0,"dub":0,"seasonInfo":null},"correctGuess":false,"wrongGuess":true,"answer":"","correctCount":2,"wrongCount":6,"startPoint":22,"videoLength":88.353,"videoUrl":"https://eudist.animemusicquiz.com/6ikdhd.webm","correctGuessPlayers":["SAVAGEGENIUS","Floth"],"listStates":[{"name":"Bommie","status":2,"score":8},{"name":"Floth","status":2,"score":7}]},{"songNumber":16,"songInfo":{"animeNames":{"english":"Memories Off 2nd","romaji":"Memories Off 2nd"},"artist":"Yuuka Nanri","composerInfo":{"artistId":10522,"name":"Chiyomaru Shikura"},"arrangerInfo":{"artistId":10481,"name":"Toshimichi Isoe"},"songName":"Futatsu no Kokoro wa","type":3,"typeNumber":0,"annId":2616,"highRisk":0,"animeScore":"5.3","animeType":"OVA","vintage":"Winter 2003","animeDifficulty":19.483830180921053,"animeTags":[],"animeGenre":["Drama","Romance"],"altAnimeNames":["Memories Off 2nd"],"altAnimeNamesAnswers":[],"siteIds":{"annId":2616,"malId":362,"kitsuId":329,"aniListId":362},"rebroadcast":0,"dub":0,"seasonInfo":{"name":"OVA","number":"2.0"}},"correctGuess":false,"wrongGuess":true,"answer":"","correctCount":0,"wrongCount":8,"startPoint":57,"videoLength":86.041,"videoUrl":"https://eudist.animemusicquiz.com/y02as5.webm","correctGuessPlayers":[],"listStates":[{"name":"gabussy","status":2,"score":null}]},{"songNumber":17,"songInfo":{"animeNames":{"english":"Darling in the FranXX","romaji":"Darling in the FranXX"},"artist":"Monique Dehaney","composerInfo":{"artistId":15698,"name":"Asami Tachibana"},"arrangerInfo":{"artistId":15698,"name":"Asami Tachibana"},"songName":"Vanquish","type":3,"typeNumber":0,"annId":19850,"highRisk":0,"animeScore":"6.8","animeType":"TV","vintage":"Winter 2018","animeDifficulty":15.693211096167795,"animeTags":["Demons","Military","Space","Male Protagonist","Tragedy","Family Life","Post-Apocalyptic","Female Protagonist","Coming of Age","Politics","Love Triangle","Survival","Super Robot","Robots","Aliens","Dystopian","Monster Girl","Kaiju","Environmental","Memory Manipulation","Conspiracy","Lost Civilization","Heterosexual","Monster Boy","Primarily Teen Cast","Found Family","Travel","Clone","Orphan","Unrequited Love","Psychosexual","Cohabitation"],"animeGenre":["Action","Drama","Mecha","Psychological","Romance","Sci-Fi"],"altAnimeNames":["Darling in the FranXX"],"altAnimeNamesAnswers":[],"siteIds":{"annId":19850,"malId":35849,"kitsuId":13600,"aniListId":99423},"rebroadcast":0,"dub":0,"seasonInfo":null},"correctGuess":false,"wrongGuess":true,"answer":"Shakugan no Shana Final","correctCount":1,"wrongCount":7,"startPoint":49,"videoLength":77.292,"videoUrl":"https://eudist.animemusicquiz.com/obyvg5.webm","correctGuessPlayers":["Bommie"],"listStates":[{"name":"gabussy","status":2,"score":null},{"name":"Dry","status":2,"score":5},{"name":"MahiruShiina","status":2,"score":8},{"name":"SAVAGEGENIUS","status":2,"score":null},{"name":"Bommie","status":2,"score":7},{"name":"HaruUrara","status":2,"score":6}]},{"songNumber":18,"songInfo":{"animeNames":{"english":"No-Rin","romaji":"Nourin"},"artist":"Yukari Tamura","composerInfo":{"artistId":15045,"name":"Shouta Tani"},"arrangerInfo":{"artistId":12497,"name":"Tomoki Kikuya"},"songName":"Cordless☆Tele☆PHONE","type":2,"typeNumber":5,"annId":15508,"highRisk":0,"animeScore":"6.4","animeType":"TV","vintage":"Winter 2014","animeDifficulty":24.85465066474781,"animeTags":["Parody","School","Male Protagonist","Idol","Love Triangle","Food","Meta","Work","Rural","Agriculture","Heterosexual"],"animeGenre":["Comedy","Ecchi","Romance"],"altAnimeNames":["No-Rin","Nourin","No-Rin","Nourin"],"altAnimeNamesAnswers":[],"siteIds":{"annId":15508,"malId":18095,"kitsuId":7782,"aniListId":18095},"rebroadcast":0,"dub":0,"seasonInfo":null},"correctGuess":false,"wrongGuess":true,"answer":"The iDOLM@STER Cinderella Girls U149","correctCount":5,"wrongCount":3,"startPoint":22,"videoLength":67.033,"videoUrl":"https://eudist.animemusicquiz.com/od232g.webm","correctGuessPlayers":["gabussy","SAVAGEGENIUS","Bommie","Floth","HaruUrara"],"listStates":[{"name":"SAVAGEGENIUS","status":2,"score":null},{"name":"Bommie","status":2,"score":6},{"name":"HaruUrara","status":2,"score":8}]},{"songNumber":19,"songInfo":{"animeNames":{"english":"GoShogun: The Time Etranger","romaji":"Sengoku Majin Goushougun: Toki no Étranger"},"artist":"Haruko Kuwana","composerInfo":{"artistId":11315,"name":"Yoshinobu Kojima"},"arrangerInfo":{"artistId":11315,"name":"Yoshinobu Kojima"},"songName":"Toki no Étranger","type":3,"typeNumber":0,"annId":670,"highRisk":0,"animeScore":"6.5","animeType":"OVA","vintage":"Spring 1985","animeDifficulty":13.827003968965023,"animeTags":["Police","Primarily Male Cast","Female Protagonist","Primarily Adult Cast","Survival","Guns","Philosophy"],"animeGenre":["Action","Sci-Fi"],"altAnimeNames":["GoShogun: The Time Etranger","Sengoku Majin Goushougun: Toki no Étranger","Time Stranger"],"altAnimeNamesAnswers":[],"siteIds":{"annId":670,"malId":2511,"kitsuId":2277,"aniListId":2511},"rebroadcast":0,"dub":0,"seasonInfo":{"name":"OVA","number":"1985"}},"correctGuess":false,"wrongGuess":true,"answer":"Wicked City","correctCount":1,"wrongCount":7,"startPoint":43,"videoLength":170.511,"videoUrl":"https://eudist.animemusicquiz.com/fabx7a.webm","correctGuessPlayers":["HaruUrara"],"listStates":[{"name":"HaruUrara","status":2,"score":7}]},{"songNumber":20,"songInfo":{"animeNames":{"english":"She, The Ultimate Weapon","romaji":"Saishuu Heiki Kanojo"},"artist":"Yuria Yato","composerInfo":{"artistId":1610,"name":"Yuria Yato"},"arrangerInfo":{"artistId":1610,"name":"Yuria Yato"},"songName":"Taion","type":3,"typeNumber":0,"annId":914,"highRisk":0,"animeScore":"6.6","animeType":"TV","vintage":"Summer 2002","animeDifficulty":16.624283203125,"animeTags":["Military","School","Seinen","Male Protagonist","Tragedy","Female Protagonist","Coming of Age","Anti-Hero","Primarily Adult Cast","War","Guns","Robots","Urban","Cyborg","Tomboy","Heterosexual","Psychosexual"],"animeGenre":["Drama","Romance","Sci-Fi"],"altAnimeNames":["SaiKano","Saishuu Heiki Kanojo","She, The Ultimate Weapon"],"altAnimeNamesAnswers":[],"siteIds":{"annId":914,"malId":529,"kitsuId":488,"aniListId":529},"rebroadcast":0,"dub":0,"seasonInfo":{"name":"TV","number":null}},"correctGuess":true,"wrongGuess":false,"answer":"SaiKano","correctCount":1,"wrongCount":7,"startPoint":72,"videoLength":96.812,"videoUrl":"https://eudist.animemusicquiz.com/uwqjlz.webm","correctGuessPlayers":["Dry"],"listStates":[{"name":"Dry","status":2,"score":9}]},{"songNumber":21,"songInfo":{"animeNames":{"english":"Girl Friend Beta","romaji":"Girlfriend (Kari)"},"artist":"Satomi Sato","composerInfo":{"artistId":12907,"name":"Yutaka Shinya"},"arrangerInfo":{"artistId":12907,"name":"Yutaka Shinya"},"songName":"Hareru kana","type":2,"typeNumber":1,"annId":16127,"highRisk":0,"animeScore":"5.4","animeType":"TV","vintage":"Fall 2014","animeDifficulty":16.660083073148975,"animeTags":["School","School Club","Primarily Female Cast","Cute Girls Doing Cute Things","Female Protagonist","Ensemble Cast"],"animeGenre":["Slice of Life"],"altAnimeNames":["Girl Friend Beta","Girlfriend (Kari)"],"altAnimeNamesAnswers":[],"siteIds":{"annId":16127,"malId":24855,"kitsuId":8632,"aniListId":20757},"rebroadcast":0,"dub":0,"seasonInfo":{"name":"TV","number":null}},"correctGuess":false,"wrongGuess":true,"answer":"Kobato.","correctCount":1,"wrongCount":7,"startPoint":4,"videoLength":88.012,"videoUrl":"https://eudist.animemusicquiz.com/xp4tpi.webm","correctGuessPlayers":["SAVAGEGENIUS"],"listStates":[{"name":"MahiruShiina","status":2,"score":4}]}]}