{
    "channina": 22.386,
    "Eryth": 21.021,
    "AKl": 20.969,
    "FayeurS": 18.882,
    "koroshiya": 17.086,
    "Deafness": 17.044,
    "Tsui": 16.872,
    "Diukes": 16.822,
    "civiltwlight": 15.889,
    "SakurabaRola": 14.877,
    "kar72": 14.509,
    "anonimus_opinion": 13.824,
    "gro": 13.769,
    "bella": 13.565,
    "claydoll1091": 13.227,
    "Thaleko": 13.214,
    "Lika": 12.847,
    "Alkios": 12.451,
    "Milar": 12.322,
    "neoburnz": 12.184,
    "SmartHardyz": 12.043,
    "Kezzy": 11.853,
    "NicoIe": 11.788,
    "RaidenMei": 11.688,
    "JuliAless64": 11.445,
    "Comete": 11.36,
    "Kuterin": 11.319,
    "comfv": 11.04,
    "Orfey": 10.771,
    "Akaze": 10.699,
    "beautiful": 10.434,
    "Dry": 10.217,
    "MD22": 9.962,
    "Progenitor": 9.657,
    "hmsuis": 9.6,
    "Provenance": 9.581,
    "chemist": 9.383,
    "mkby": 9.194,
    "AnnaYanami": 9.129,
    "Saiki": 9.126,
    "yasashiikumo": 9.051,
    "spanky": 8.872,
    "uomi": 8.432,
    "kishua": 8.378,
    "Fumiii": 8.337,
    "mahzrunner": 7.91,
    "Skychael": 7.823,
    "Ephemeral": 7.663,
    "Mika_tw": 7.563,
    "Kenzou_Tenma": 7.439,
    "Janoxx": 7.426,
    "xeyz": 7.138,
    "uy5gf": 6.822,
    "VuhrCulls": 6.522,
    "Patoche49": 6.429,
    "Konsumenci": 6.262,
    "OkitaNobu": 6.092,
    "Catge": 5.973,
    "chommy": 5.232
}