{
    "watashiii": 158.74,
    "channina": 158.72,
    "Eryth": 145.06,
    "ArronChu": 144.61,
    "koroshiya": 133.91,
    "Sniparook": 127.69,
    "FORTNAYT": 123.08,
    "civiltwlight": 122.82,
    "Tsui": 119.7,
    "kar72": 113.64,
    "Thaleko": 113.57,
    "Chata": 112.4,
    "Dry": 112.308,
    "Diukes": 110.785,
    "eternity": 110.68,
    "PoolNoodle": 108.56,
    "Nicole": 108.02,
    "mrwolf2": 107.69,
    "cafezinho": 104.27,
    "ShiinaMahiru": 104.18,
    "yasashiikumo": 104.173,
    "comfv": 101.85,
    "mahzrunner": 97.87,
    "Lika": 96.43,
    "Provenance": 96.09,
    "Alkios": 95.66,
    "HaruUrara": 95.23,
    "neoburnz": 94.22,
    "JuliAless64": 94.15,
    "Progenitor": 93.59,
    "Pile": 93.59,
    "MahiruShiina": 93.57,
    "chaabdu92": 92.52,
    "_nadeshiko": 91.83,
    "hmsuis": 91.54,
    "Jakemonkey": 91.37,
    "Skychael": 90.94,
    "Flato": 90.32,
    "Hyonoka": 90.22,
    "AnnaYanami": 89.61,
    "Baikinman": 89.51,
    "florenz": 89.42,
    "Yolowolf75": 89.25,
    "ruuka": 86.5,
    "Neumann": 86.21,
    "chemist": 85.1,
    "Fumiii": 84.7,
    "OkitaNobu": 84.32,
    "xeyz": 83.55,
    "Janoxx": 83.4,
    "yashadox": 82.79,
    "ss_r_white_pony": 82.08,
    "Saiki": 80.142,
    "Patoche49": 78.47,
    "Tsuni": 75.2,
    "arpia97": 74.85,
    "Rhummy": 69.71,
    "FoopyPoopy": 68.36
}