{
    "FORTNAYT": 177.89,
    "Stunar": 161.29,
    "YuriMeguri": 160.99,
    "ArronChu": 149.06,
    "Thaleko": 144.563,
    "PoolNoodle": 144.496,
    "watashiii": 143.68,
    "kar72": 139.7,
    "civiltwlight": 138.235,
    "Tsui": 137.742,
    "neoburnz": 135.419,
    "neptune": 133.52,
    "revel": 133.34,
    "Milar": 132.347,
    "apurplenose": 130.176,
    "ShiinaMahiru": 128.293,
    "kabigon": 128.16,
    "Renzou": 126.94,
    "Chata": 124.964,
    "Zental": 124.73,
    "cafezinho": 123.726,
    "Progenitor": 122.52,
    "Komari": 122.007,
    "Nephirea": 121.46,
    "Mami": 121.16,
    "bamboo": 121.02,
    "Noru": 120.7,
    "JuliAless64": 120.51,
    "Lika": 120.17,
    "CipherKai": 119.914,
    "MahiruShiina": 119.823,
    "kaededayo": 119.75,
    "Beokros": 119.354,
    "claydoll1091": 117.89,
    "doomchicken": 117.32,
    "HaruUrara": 117.167,
    "Neumann": 116.23,
    "Bofu": 116.19,
    "ShelterRin": 115.691,
    "Selaph": 115.33,
    "Emdiel": 115.24,
    "harges": 115.142,
    "Flato": 114.836,
    "mrwolf2": 114.56,
    "Maki04": 114.4,
    "moosepi": 114.14,
    "Diukes": 113.49,
    "peeku": 113.26,
    "florenz": 113.193,
    "Sniparook": 112.63,
    "AitsukiNakuru": 112.397,
    "Legitted": 112.32,
    "Pile": 112.284,
    "Floth": 111.995,
    "hmsuis": 111.669,
    "oh95": 111.22,
    "mangoss": 110.949,
    "miiarad": 109.959,
    "Fumiii": 109.497,
    "yasashiikumo": 109.407,
    "Jakemonkey": 108.925,
    "tapumomo": 108.85,
    "Zozo": 108.73,
    "IrinaShidou": 108.606,
    "Shuuka": 108.54,
    "ruuka": 108.421,
    "Spitzell": 108.153,
    "Comete": 107.67,
    "beautiful": 107.56,
    "Provenance": 107.516,
    "AnnaYanami": 107.293,
    "chaabdu92": 106.843,
    "liljakatsuragi": 106.728,
    "Swapin": 106.38,
    "Kirox": 106.35,
    "paperyoshi10": 106.22,
    "HiHi": 106.2,
    "AnotherWish": 106.06,
    "kabao": 105.99,
    "2skr": 105.57,
    "Lakumix": 105.565,
    "Skychael": 105.359,
    "YunnN": 105.12,
    "accelerator11": 105.05,
    "md22": 104.644,
    "Hejsan": 104.53,
    "Jessi": 104.52,
    "Alkios": 103.86,
    "DKing20": 103.65,
    "NMapper": 103.489,
    "pomo": 102.619,
    "Solosion": 102.61,
    "Heleos": 102.568,
    "sharet": 102.27,
    "KNotAnyMore": 101.913,
    "jaimeywea": 101.788,
    "Serozero": 101.552,
    "redeyes": 101.34,
    "ac9123": 101.34,
    "Dry": 101.31,
    "Zeal_Kido": 101.27,
    "Janoxx": 101.221,
    "_nadeshiko": 101.029,
    "joey": 100.675,
    "Orfey": 100.52,
    "sssthnoob": 100.41,
    "Naizuri": 100.104,
    "Keizan": 99.72,
    "FUCK_AMQ": 99.61,
    "ss_r_white_pony": 99.577,
    "chommy": 99.546,
    "Dav1d1": 99.061,
    "fiftypercentweeb": 98.95,
    "Baikinman": 98.82,
    "Andrey_K": 97.99,
    "Konsumenci": 97.662,
    "rorf": 96.518,
    "Shadow": 96.445,
    "LelPop": 96.35,
    "mahzrunner": 95.517,
    "Bommie": 95.406,
    "chemist": 95.289,
    "Isekaijoucho": 95.144,
    "ranny": 94.895,
    "Jube": 94.45,
    "Tugia": 94.237,
    "oolli": 93.822,
    "FurLain": 93.82,
    "qwecocacola": 93.811,
    "CM02": 92.2,
    "Mayottatoki": 92.174,
    "zokie": 91.92,
    "Nefregar": 91.13,
    "Torradinhas": 90.766,
    "thjalago": 90.28,
    "metak": 89.815,
    "anicomi": 89.793,
    "psirockin": 89.646,
    "Loomi": 89.55,
    "Porte": 89.542,
    "PotassiumF": 89.402,
    "Feynox_": 89.09,
    "FeyFey": 88.9,
    "Catge": 88.81,
    "Vr0003": 88.591,
    "ChrisLefko": 88.52,
    "Patoche49": 88.415,
    "BigSmo": 88.32,
    "rinshantsumo": 88.27,
    "Gabetin": 88.076,
    "Megu29": 87.07,
    "benevelante": 86.94,
    "legrandort": 86.927,
    "Bullymel36": 86.8,
    "VuhrCulls": 86.78,
    "MisheruDesu": 86.64,
    "tskr": 86.529,
    "LordGrond": 85.743,
    "Goko8765": 85.68,
    "uy5gf": 85.22,
    "Lightning": 84.765,
    "keysha18": 84.67,
    "Yolowolf75": 84.34,
    "YellowRose": 84.12,
    "Kyuuuu": 83.864,
    "Shiku": 83.85,
    "arpia97": 83.765,
    "OkitaNobu": 83.434,
    "xeyz": 82.744,
    "Efe": 82.3,
    "inta": 82.227,
    "Spartric": 81.297,
    "Najeem": 79.916,
    "pekorrat": 78.54,
    "TateyamaAyano": 78.263,
    "Hotpot": 78.01,
    "l_elf10": 77.94,
    "Cindergoat": 77.57,
    "anatharax": 77.456,
    "Unborned": 77.34,
    "JustAWeirdo": 77.062,
    "Zarelyyyx": 76.85,
    "FoopyPoopy": 76.559,
    "IAmAsianNoob": 75.821,
    "icefeed2": 75.72,
    "atsui": 74.96,
    "Caramel36": 74.021,
    "hubcioskubcio": 73.832,
    "Dovixx": 73.628,
    "ThePieGod": 73.51,
    "Luna": 72.524,
    "MythAndroid": 71.84,
    "I_dont_like_loli": 71.69,
    "JaneRemover": 71.55,
    "Wiwmek": 71.14,
    "Tsuni": 69.35,
    "SaoriHayami": 69.253,
    "OSXtrafton": 68.0,
    "Nomu": 66.56,
    "hakohoka": 66.198,
    "ElJuanchi": 65.654,
    "yonyon": 60.77,
    "brandon_K": 60.593,
    "Nunuchu42": 60.044,
    "Whales6978": 56.591,
    "erzakuran": 55.096,
    "WatchPotat": 47.65
}