{
    "AKl": 20.688,
    "PoolNoodle": 20.294,
    "Deafness": 20.211,
    "FORTNAYT": 19.808,
    "OffenseArmor": 19.154,
    "Thaleko": 18.957,
    "remake": 18.48,
    "civiltwlight": 18.258,
    "Nazemeiyue": 18.057,
    "cupcakke": 17.855,
    "Math_": 17.777,
    "neoburnz": 17.739,
    "kar72": 17.605,
    "revel": 17.372,
    "Sniparook": 17.11,
    "SaroArsten": 17.1,
    "bella": 16.883,
    "GyroInmobile": 16.714,
    "Milar": 16.614,
    "Bofu": 16.583,
    "Renzou": 16.451,
    "Kezzy": 15.697,
    "neptune": 15.693,
    "JuliAless64": 15.663,
    "kabigon": 15.572,
    "peeku": 15.439,
    "ShiratoriAmaha": 15.382,
    "Noru": 15.36,
    "apurplenose": 15.21,
    "Nephirea": 15.204,
    "Emdiel": 15.147,
    "Wuffles": 15.034,
    "Kawada6": 14.96,
    "Diukes": 14.933,
    "supersmooth": 14.855,
    "Mami": 14.828,
    "oh95": 14.511,
    "moosepi": 14.482,
    "Zental": 14.462,
    "kaededayo": 14.39,
    "cafezinho": 14.178,
    "doomchicken": 14.159,
    "Floth": 14.111,
    "LaggyGlassySky": 14.061,
    "claydoll1091": 13.972,
    "Fumiii": 13.953,
    "comfv": 13.952,
    "anonimus_opinion": 13.942,
    "RaidenMei": 13.817,
    "Maki04": 13.683,
    "Progenitor": 13.528,
    "Jessi": 13.525,
    "Beokros": 13.511,
    "Pratasz": 13.507,
    "bamboo": 13.446,
    "mkby": 13.42,
    "Mayottatoki": 13.401,
    "SayuriDate": 13.381,
    "MrWolf": 13.271,
    "Flato": 13.252,
    "Ephemeral": 13.211,
    "Python": 13.205,
    "ruuka": 13.19,
    "Comete": 13.074,
    "MizukiNana": 12.95,
    "Saiki": 12.93,
    "kishua": 12.732,
    "DKing20": 12.689,
    "mahzrunner": 12.54,
    "Pile": 12.537,
    "hmsuis": 12.509,
    "rorf": 12.503,
    "beautiful": 12.266,
    "KNotAnyMore": 12.258,
    "Zeal_Kido": 12.225,
    "uomi": 12.203,
    "ShelterRin": 12.195,
    "AitsukiNakuru": 12.193,
    "CipherKai": 12.192,
    "Orfey": 12.128,
    "Swapin": 12.104,
    "_nadeshiko": 12.032,
    "Time2Hack": 12.027,
    "chaabdu92": 12.013,
    "Dry": 12.011,
    "Jakemonkey": 11.964,
    "1Godly": 11.963,
    "LelPop": 11.956,
    "tapumomo": 11.942,
    "lakumix": 11.899,
    "chemist": 11.825,
    "Kuterin": 11.811,
    "Konsumenci": 11.799,
    "Wolbachia": 11.775,
    "Alkios": 11.759,
    "ss_r_white_pony": 11.729,
    "liljakatsuragi": 11.595,
    "miiarad": 11.428,
    "Solosion": 11.4,
    "Provenance": 11.389,
    "ShiroganeLily": 11.382,
    "Bommie": 11.379,
    "Torradinhas": 11.268,
    "sssthnoob": 11.186,
    "florenz": 11.18,
    "GGius": 11.143,
    "Kenzou_Tenma": 11.131,
    "Animerod": 11.112,
    "Yolowolf75": 11.02,
    "Skychael": 11.009,
    "yasashiikumo": 10.973,
    "Kirox": 10.872,
    "Shadow": 10.827,
    "Janoxx": 10.82,
    "AnnaYanami": 10.79,
    "benevelante": 10.789,
    "Zozo": 10.698,
    "Spitzell": 10.602,
    "Sgtvp": 10.569,
    "Lightning": 10.535,
    "YunnN": 10.468,
    "atsui": 10.392,
    "ChrisLefko": 10.383,
    "uy5gf": 10.299,
    "Vr0003": 10.279,
    "Serozero": 10.26,
    "qwecocacola": 10.259,
    "AnotherWish": 10.227,
    "VuhrCulls": 10.203,
    "rna": 10.186,
    "Kyuuuu": 10.144,
    "MD22": 9.927,
    "Porte": 9.822,
    "oolli": 9.801,
    "fiftypercentweeb": 9.78,
    "Naizuri": 9.692,
    "Andrey_K": 9.681,
    "legrandort": 9.634,
    "PotassiumF": 9.553,
    "BigSmo": 9.548,
    "zokie": 9.487,
    "tskr": 9.405,
    "kabao": 9.403,
    "Spartric": 9.36,
    "I_dont_like_loli": 9.287,
    "Patoche49": 9.211,
    "Gua": 9.165,
    "ranny": 9.116,
    "Nefregar": 9.051,
    "Oshino_bu": 9.029,
    "Shiku": 8.97,
    "2skr": 8.955,
    "psirockin": 8.819,
    "CM02": 8.757,
    "YellowRose": 8.701,
    "xeyz": 8.689,
    "inta": 8.628,
    "PotatoSnipez": 8.596,
    "Catge": 8.514,
    "keysha18": 8.486,
    "chommy": 8.424,
    "IAmAsianNoob": 8.388,
    "gw13": 8.305,
    "arpia97": 8.274,
    "JustAWeirdo": 8.209,
    "KanaKanowata": 8.135,
    "Goko8765": 8.124,
    "MythAndroid": 8.097,
    "OkitaNobu": 7.913,
    "Megu29": 7.694,
    "anicomi": 7.52,
    "TateyamaAyano": 7.413,
    "Rhummy": 7.193,
    "hubcioskubcio": 7.061,
    "Mangalodon": 7.045,
    "anatharax": 7.03,
    "MapleSyyrup": 6.972,
    "Tsuni": 6.723,
    "Gameplayer299": 6.434,
    "ElJuanchi": 6.43,
    "FoopyPoopy": 6.21,
    "LordGrond": 6.154,
    "kuusetsu": 5.904,
    "Azure10": 5.901,
    "HerofTime": 5.69,
    "OSXtrafton": 5.459,
    "brandon_K": 5.435,
    "erzakuran": 5.368
}